evenet/__init__.py
evenet/engine.py
evenet/predict.py
evenet/shared.py
evenet/train.py
evenet/control/event_info.py
evenet/control/global_config.py
evenet/dataset/__init__.py
evenet/dataset/preprocess.py
evenet/dataset/types.py
evenet/network/evenet_model.py
evenet/network/body/embedding.py
evenet/network/body/normalizer.py
evenet/network/body/object_encoder.py
evenet/network/callbacks/predict_writer.py
evenet/network/heads/assignment/assignment_head.py
evenet/network/heads/assignment/symmetric_attention.py
evenet/network/heads/classification/classification_head.py
evenet/network/heads/generation/generation_head.py
evenet/network/heads/segmentation/segmentation_head.py
evenet/network/layers/activation.py
evenet/network/layers/debug_layer.py
evenet/network/layers/linear_block.py
evenet/network/layers/mask.py
evenet/network/layers/norm.py
evenet/network/layers/transformer.py
evenet/network/layers/utils.py
evenet/network/loss/assignment.py
evenet/network/loss/classification.py
evenet/network/loss/famo.py
evenet/network/loss/generation.py
evenet/network/loss/grad_norm.py
evenet/network/loss/regression.py
evenet/network/loss/segmentation.py
evenet/network/metrics/assignment.py
evenet/network/metrics/classification.py
evenet/network/metrics/debug_evaluator.py
evenet/network/metrics/general_comparison.py
evenet/network/metrics/generation.py
evenet/network/metrics/predict_assignment.py
evenet/network/metrics/predict_assignment_numba.py
evenet/network/metrics/segmentation.py
evenet/utilities/debug_tool.py
evenet/utilities/diffusion_sampler.py
evenet/utilities/ema.py
evenet/utilities/group_theory.py
evenet/utilities/linear_form.py
evenet/utilities/logger.py
evenet/utilities/masked_softmax_no_gradient.py
evenet/utilities/task_scheduler.py
evenet/utilities/tool.py
evenet-0.1.2.dist-info/METADATA
evenet-0.1.2.dist-info/WHEEL
evenet-0.1.2.dist-info/entry_points.txt
evenet-0.1.2.dist-info/top_level.txt
evenet-0.1.2.dist-info/RECORD
