Metadata-Version: 2.4
Name: evenet
Version: 0.1.2
Summary: Training and inference entry points for the EveNet event processing model.
Author: Yulei Zhang, Ting-Hsiang Hsu
Requires-Python: >=3.12
